[{"version":1,"timestamp":"2018-01-12 23:12:11 +0100","longitude":-1,"latitude":-1,"altitude":67.0,"accuracy_v":0,"accuracy_h":7,"speed":3.312000036239624,"duration":2612,"distance":0,"elevation_gain":0,"elevation_loss":0},
{"version":1,"timestamp":"2018-01-12 23:12:26 +0100","longitude":-1,"latitude":-1,"altitude":66.0,"accuracy_v":0,"accuracy_h":13,"speed":8.758468627929688,"duration":17618,"distance":34,"elevation_gain":0,"elevation_loss":1},
{"version":1,"timestamp":"2018-01-12 23:12:38 +0100","longitude":-1,"latitude":-1,"altitude":66.0,"accuracy_v":0,"accuracy_h":7,"speed":7.217700004577637,"duration":29619,"distance":72,"elevation_gain":0,"elevation_loss":1},
{"version":1,"timestamp":"2018-01-12 23:12:45 +0100","longitude":-1,"latitude":-1,"altitude":65.0,"accuracy_v":0,"accuracy_h":7,"speed":6.84895133972168,"duration":36620,"distance":93,"elevation_gain":0,"elevation_loss":2},
{"version":1,"timestamp":"2018-01-12 23:12:52 +0100","longitude":-1,"latitude":-1,"altitude":68.0,"accuracy_v":0,"accuracy_h":10,"speed":5.6700758934021,"duration":43615,"distance":112,"elevation_gain":3,"elevation_loss":2},
{"version":1,"timestamp":"2018-01-12 23:12:59 +0100","longitude":-1,"latitude":-1,"altitude":71.0,"accuracy_v":0,"accuracy_h":12,"speed":12.854142189025879,"duration":50618,"distance":148,"elevation_gain":6,"elevation_loss":2},
{"version":1,"timestamp":"2018-01-12 23:13:11 +0100","longitude":-1,"latitude":-1,"altitude":82.0,"accuracy_v":0,"accuracy_h":16,"speed":8.53796100616455,"duration":62620,"distance":182,"elevation_gain":17,"elevation_loss":2},
{"version":1,"timestamp":"2018-01-12 23:13:28 +0100","longitude":-1,"latitude":-1,"altitude":79.0,"accuracy_v":0,"accuracy_h":10,"speed":6.030843257904053,"duration":79614,"distance":220,"elevation_gain":17,"elevation_loss":5},
{"version":1,"timestamp":"2018-01-12 23:13:42 +0100","longitude":-1,"latitude":-1,"altitude":68.0,"accuracy_v":0,"accuracy_h":12,"speed":5.849339962005615,"duration":93620,"distance":250,"elevation_gain":17,"elevation_loss":16},
{"version":1,"timestamp":"2018-01-12 23:13:51 +0100","longitude":-1,"latitude":-1,"altitude":66.0,"accuracy_v":0,"accuracy_h":15,"speed":5.501250743865967,"duration":102626,"distance":275,"elevation_gain":17,"elevation_loss":18},
{"version":1,"timestamp":"2018-01-12 23:13:58 +0100","longitude":-1,"latitude":-1,"altitude":74.0,"accuracy_v":0,"accuracy_h":13,"speed":6.603208065032959,"duration":109614,"distance":312,"elevation_gain":25,"elevation_loss":18},
{"version":1,"timestamp":"2018-01-12 23:14:06 +0100","longitude":-1,"latitude":-1,"altitude":77.0,"accuracy_v":0,"accuracy_h":21,"speed":7.099468231201172,"duration":117622,"distance":322,"elevation_gain":28,"elevation_loss":18},
{"version":1,"timestamp":"2018-01-12 23:14:10 +0100","longitude":-1,"latitude":-1,"altitude":65.0,"accuracy_v":0,"accuracy_h":18,"speed":7.313015460968018,"duration":121622,"distance":335,"elevation_gain":28,"elevation_loss":30},
{"version":1,"timestamp":"2018-01-12 23:14:13 +0100","longitude":-1,"latitude":-1,"altitude":69.0,"accuracy_v":0,"accuracy_h":12,"speed":4.254068374633789,"duration":124616,"distance":366,"elevation_gain":32,"elevation_loss":30},
{"version":1,"timestamp":"2018-01-12 23:14:20 +0100","longitude":-1,"latitude":-1,"altitude":70.0,"accuracy_v":0,"accuracy_h":18,"speed":7.263876914978027,"duration":131634,"distance":402,"elevation_gain":33,"elevation_loss":30},
{"version":1,"timestamp":"2018-01-12 23:14:33 +0100","longitude":-1,"latitude":-1,"altitude":69.0,"accuracy_v":0,"accuracy_h":18,"speed":6.572281837463379,"duration":144615,"distance":422,"elevation_gain":33,"elevation_loss":31},
{"version":1,"timestamp":"2018-01-12 23:14:39 +0100","longitude":-1,"latitude":-1,"altitude":68.0,"accuracy_v":0,"accuracy_h":19,"speed":7.961139678955078,"duration":150617,"distance":447,"elevation_gain":33,"elevation_loss":32},
{"version":1,"timestamp":"2018-01-12 23:14:47 +0100","longitude":-1,"latitude":-1,"altitude":66.0,"accuracy_v":0,"accuracy_h":19,"speed":6.838230609893799,"duration":158626,"distance":471,"elevation_gain":33,"elevation_loss":34},
{"version":1,"timestamp":"2018-01-12 23:14:53 +0100","longitude":-1,"latitude":-1,"altitude":68.0,"accuracy_v":0,"accuracy_h":16,"speed":6.2667107582092285,"duration":164625,"distance":491,"elevation_gain":35,"elevation_loss":34},
{"version":1,"timestamp":"2018-01-12 23:14:59 +0100","longitude":-1,"latitude":-1,"altitude":67.0,"accuracy_v":0,"accuracy_h":16,"speed":7.137210845947266,"duration":170621,"distance":525,"elevation_gain":35,"elevation_loss":35},
{"version":1,"timestamp":"2018-01-12 23:15:08 +0100","longitude":-1,"latitude":-1,"altitude":72.0,"accuracy_v":0,"accuracy_h":18,"speed":10.016807556152344,"duration":179620,"distance":559,"elevation_gain":40,"elevation_loss":35},
{"version":1,"timestamp":"2018-01-12 23:15:18 +0100","longitude":-1,"latitude":-1,"altitude":74.0,"accuracy_v":0,"accuracy_h":10,"speed":10.483846664428711,"duration":189625,"distance":599,"elevation_gain":42,"elevation_loss":35},
{"version":1,"timestamp":"2018-01-12 23:15:30 +0100","longitude":-1,"latitude":-1,"altitude":71.0,"accuracy_v":0,"accuracy_h":4,"speed":11.772391319274902,"duration":201633,"distance":639,"elevation_gain":42,"elevation_loss":38},
{"version":1,"timestamp":"2018-01-12 23:15:46 +0100","longitude":-1,"latitude":-1,"altitude":73.0,"accuracy_v":0,"accuracy_h":10,"speed":7.628631591796875,"duration":217620,"distance":675,"elevation_gain":44,"elevation_loss":38},
{"version":1,"timestamp":"2018-01-12 23:16:01 +0100","longitude":-1,"latitude":-1,"altitude":76.0,"accuracy_v":0,"accuracy_h":9,"speed":6.6147661209106445,"duration":232617,"distance":714,"elevation_gain":47,"elevation_loss":38},
{"version":1,"timestamp":"2018-01-12 23:16:11 +0100","longitude":-1,"latitude":-1,"altitude":72.0,"accuracy_v":0,"accuracy_h":13,"speed":8.023807525634766,"duration":242616,"distance":749,"elevation_gain":47,"elevation_loss":42},
{"version":1,"timestamp":"2018-01-12 23:16:25 +0100","longitude":-1,"latitude":-1,"altitude":75.0,"accuracy_v":0,"accuracy_h":12,"speed":8.49239730834961,"duration":256622,"distance":786,"elevation_gain":50,"elevation_loss":42},
{"version":1,"timestamp":"2018-01-12 23:16:39 +0100","longitude":-1,"latitude":-1,"altitude":73.0,"accuracy_v":0,"accuracy_h":18,"speed":6.163599014282227,"duration":270619,"distance":816,"elevation_gain":50,"elevation_loss":44},
{"version":1,"timestamp":"2018-01-12 23:16:51 +0100","longitude":-1,"latitude":-1,"altitude":69.0,"accuracy_v":0,"accuracy_h":22,"speed":5.634230613708496,"duration":282615,"distance":834,"elevation_gain":50,"elevation_loss":48},
{"version":1,"timestamp":"2018-01-12 23:16:56 +0100","longitude":-1,"latitude":-1,"altitude":73.0,"accuracy_v":0,"accuracy_h":21,"speed":7.150829792022705,"duration":287615,"distance":859,"elevation_gain":54,"elevation_loss":48},
{"version":1,"timestamp":"2018-01-12 23:17:05 +0100","longitude":-1,"latitude":-1,"altitude":74.0,"accuracy_v":0,"accuracy_h":18,"speed":5.99388313293457,"duration":296616,"distance":876,"elevation_gain":55,"elevation_loss":48},
{"version":1,"timestamp":"2018-01-12 23:17:09 +0100","longitude":-1,"latitude":-1,"altitude":71.0,"accuracy_v":0,"accuracy_h":16,"speed":5.794466018676758,"duration":300619,"distance":905,"elevation_gain":55,"elevation_loss":51},
{"version":1,"timestamp":"2018-01-12 23:17:17 +0100","longitude":-1,"latitude":-1,"altitude":72.0,"accuracy_v":0,"accuracy_h":16,"speed":5.685827732086182,"duration":308612,"distance":925,"elevation_gain":56,"elevation_loss":51},
{"version":1,"timestamp":"2018-01-12 23:17:23 +0100","longitude":-1,"latitude":-1,"altitude":74.0,"accuracy_v":0,"accuracy_h":15,"speed":6.688793182373047,"duration":314620,"distance":951,"elevation_gain":58,"elevation_loss":51},
{"version":1,"timestamp":"2018-01-12 23:17:30 +0100","longitude":-1,"latitude":-1,"altitude":71.0,"accuracy_v":0,"accuracy_h":15,"speed":8.585668563842773,"duration":321622,"distance":987,"elevation_gain":58,"elevation_loss":54},
{"version":1,"timestamp":"2018-01-12 23:17:40 +0100","longitude":-1,"latitude":-1,"altitude":77.0,"accuracy_v":0,"accuracy_h":15,"speed":10.713874816894531,"duration":331622,"distance":1020,"elevation_gain":64,"elevation_loss":54},
{"version":1,"timestamp":"2018-01-12 23:17:50 +0100","longitude":-1,"latitude":-1,"altitude":71.0,"accuracy_v":0,"accuracy_h":18,"speed":10.416523933410645,"duration":341618,"distance":1053,"elevation_gain":64,"elevation_loss":60},
{"version":1,"timestamp":"2018-01-12 23:18:00 +0100","longitude":-1,"latitude":-1,"altitude":71.0,"accuracy_v":0,"accuracy_h":16,"speed":8.18838119506836,"duration":351613,"distance":1084,"elevation_gain":64,"elevation_loss":60},
{"version":1,"timestamp":"2018-01-12 23:18:10 +0100","longitude":-1,"latitude":-1,"altitude":73.0,"accuracy_v":0,"accuracy_h":15,"speed":9.266266822814941,"duration":361615,"distance":1122,"elevation_gain":66,"elevation_loss":60},
{"version":1,"timestamp":"2018-01-12 23:18:22 +0100","longitude":-1,"latitude":-1,"altitude":78.0,"accuracy_v":0,"accuracy_h":16,"speed":9.800674438476562,"duration":373618,"distance":1158,"elevation_gain":71,"elevation_loss":60},
{"version":1,"timestamp":"2018-01-12 23:18:34 +0100","longitude":-1,"latitude":-1,"altitude":77.0,"accuracy_v":0,"accuracy_h":15,"speed":9.34162425994873,"duration":385625,"distance":1194,"elevation_gain":71,"elevation_loss":61},
{"version":1,"timestamp":"2018-01-12 23:18:50 +0100","longitude":-1,"latitude":-1,"altitude":78.0,"accuracy_v":0,"accuracy_h":15,"speed":6.369099140167236,"duration":401622,"distance":1231,"elevation_gain":72,"elevation_loss":61},
{"version":1,"timestamp":"2018-01-12 23:19:06 +0100","longitude":-1,"latitude":-1,"altitude":77.0,"accuracy_v":0,"accuracy_h":15,"speed":6.551905632019043,"duration":417613,"distance":1263,"elevation_gain":72,"elevation_loss":62},
{"version":1,"timestamp":"2018-01-12 23:19:16 +0100","longitude":-1,"latitude":-1,"altitude":80.0,"accuracy_v":0,"accuracy_h":4,"speed":8.366560935974121,"duration":427623,"distance":1300,"elevation_gain":75,"elevation_loss":62},
{"version":1,"timestamp":"2018-01-12 23:19:28 +0100","longitude":-1,"latitude":-1,"altitude":80.0,"accuracy_v":0,"accuracy_h":4,"speed":9.489081382751465,"duration":439617,"distance":1341,"elevation_gain":75,"elevation_loss":62},
{"version":1,"timestamp":"2018-01-12 23:19:43 +0100","longitude":-1,"latitude":-1,"altitude":78.0,"accuracy_v":0,"accuracy_h":7,"speed":8.68861198425293,"duration":454633,"distance":1381,"elevation_gain":75,"elevation_loss":64},
{"version":1,"timestamp":"2018-01-12 23:19:55 +0100","longitude":-1,"latitude":-1,"altitude":75.0,"accuracy_v":0,"accuracy_h":6,"speed":10.882433891296387,"duration":466623,"distance":1421,"elevation_gain":75,"elevation_loss":67},
{"version":1,"timestamp":"2018-01-12 23:20:10 +0100","longitude":-1,"latitude":-1,"altitude":74.0,"accuracy_v":0,"accuracy_h":7,"speed":8.697338104248047,"duration":481620,"distance":1461,"elevation_gain":75,"elevation_loss":68},
{"version":1,"timestamp":"2018-01-12 23:20:23 +0100","longitude":-1,"latitude":-1,"altitude":76.0,"accuracy_v":0,"accuracy_h":9,"speed":9.577402114868164,"duration":494625,"distance":1501,"elevation_gain":77,"elevation_loss":68},
{"version":1,"timestamp":"2018-01-12 23:20:36 +0100","longitude":-1,"latitude":-1,"altitude":73.0,"accuracy_v":0,"accuracy_h":6,"speed":8.999608039855957,"duration":507624,"distance":1540,"elevation_gain":77,"elevation_loss":71},
{"version":1,"timestamp":"2018-01-12 23:20:50 +0100","longitude":-1,"latitude":-1,"altitude":73.0,"accuracy_v":0,"accuracy_h":7,"speed":8.778643608093262,"duration":521612,"distance":1579,"elevation_gain":77,"elevation_loss":71},
{"version":1,"timestamp":"2018-01-12 23:21:01 +0100","longitude":-1,"latitude":-1,"altitude":72.0,"accuracy_v":0,"accuracy_h":9,"speed":9.382160186767578,"duration":532619,"distance":1617,"elevation_gain":77,"elevation_loss":72},
{"version":1,"timestamp":"2018-01-12 23:21:14 +0100","longitude":-1,"latitude":-1,"altitude":75.0,"accuracy_v":0,"accuracy_h":6,"speed":8.434466361999512,"duration":545619,"distance":1657,"elevation_gain":80,"elevation_loss":72},
{"version":1,"timestamp":"2018-01-12 23:21:31 +0100","longitude":-1,"latitude":-1,"altitude":72.0,"accuracy_v":0,"accuracy_h":7,"speed":5.565301895141602,"duration":562615,"distance":1694,"elevation_gain":80,"elevation_loss":75},
{"version":1,"timestamp":"2018-01-12 23:21:42 +0100","longitude":-1,"latitude":-1,"altitude":70.0,"accuracy_v":0,"accuracy_h":7,"speed":9.764753341674805,"duration":573611,"distance":1733,"elevation_gain":80,"elevation_loss":77},
{"version":1,"timestamp":"2018-01-12 23:21:54 +0100","longitude":-1,"latitude":-1,"altitude":70.0,"accuracy_v":0,"accuracy_h":7,"speed":10.652873039245605,"duration":585608,"distance":1772,"elevation_gain":80,"elevation_loss":77},
{"version":1,"timestamp":"2018-01-12 23:22:07 +0100","longitude":-1,"latitude":-1,"altitude":69.0,"accuracy_v":0,"accuracy_h":10,"speed":8.181546211242676,"duration":598614,"distance":1810,"elevation_gain":80,"elevation_loss":78},
{"version":1,"timestamp":"2018-01-12 23:22:11 +0100","longitude":-1,"latitude":-1,"altitude":67.0,"accuracy_v":0,"accuracy_h":9,"speed":9.405774116516113,"duration":602617,"distance":1822,"elevation_gain":80,"elevation_loss":80},
{"version":1,"timestamp":"2018-01-12 23:22:22 +0100","longitude":-1,"latitude":-1,"altitude":71.0,"accuracy_v":0,"accuracy_h":12,"speed":6.696129322052002,"duration":613612,"distance":1847,"elevation_gain":84,"elevation_loss":80},
{"version":1,"timestamp":"2018-01-12 23:22:33 +0100","longitude":-1,"latitude":-1,"altitude":67.0,"accuracy_v":0,"accuracy_h":7,"speed":6.936583995819092,"duration":624624,"distance":1883,"elevation_gain":84,"elevation_loss":84},
{"version":1,"timestamp":"2018-01-12 23:22:43 +0100","longitude":-1,"latitude":-1,"altitude":73.0,"accuracy_v":0,"accuracy_h":9,"speed":11.711769104003906,"duration":634615,"distance":1923,"elevation_gain":90,"elevation_loss":84},
{"version":1,"timestamp":"2018-01-12 23:22:55 +0100","longitude":-1,"latitude":-1,"altitude":72.0,"accuracy_v":0,"accuracy_h":12,"speed":9.209785461425781,"duration":646618,"distance":1960,"elevation_gain":90,"elevation_loss":85},
{"version":1,"timestamp":"2018-01-12 23:23:05 +0100","longitude":-1,"latitude":-1,"altitude":76.0,"accuracy_v":0,"accuracy_h":15,"speed":11.52764892578125,"duration":656623,"distance":1996,"elevation_gain":94,"elevation_loss":85},
{"version":1,"timestamp":"2018-01-12 23:23:15 +0100","longitude":-1,"latitude":-1,"altitude":74.0,"accuracy_v":0,"accuracy_h":7,"speed":9.868508338928223,"duration":666618,"distance":2034,"elevation_gain":94,"elevation_loss":87},
{"version":1,"timestamp":"2018-01-12 23:23:26 +0100","longitude":-1,"latitude":-1,"altitude":72.0,"accuracy_v":0,"accuracy_h":7,"speed":10.827859878540039,"duration":677636,"distance":2074,"elevation_gain":94,"elevation_loss":89},
{"version":1,"timestamp":"2018-01-12 23:23:37 +0100","longitude":-1,"latitude":-1,"altitude":72.0,"accuracy_v":0,"accuracy_h":7,"speed":11.527569770812988,"duration":688617,"distance":2115,"elevation_gain":94,"elevation_loss":89},
{"version":1,"timestamp":"2018-01-12 23:23:49 +0100","longitude":-1,"latitude":-1,"altitude":70.0,"accuracy_v":0,"accuracy_h":12,"speed":10.613898277282715,"duration":700619,"distance":2153,"elevation_gain":94,"elevation_loss":91},
{"version":1,"timestamp":"2018-01-12 23:23:58 +0100","longitude":-1,"latitude":-1,"altitude":72.0,"accuracy_v":0,"accuracy_h":6,"speed":7.309182643890381,"duration":709610,"distance":2179,"elevation_gain":96,"elevation_loss":91},
{"version":1,"timestamp":"2018-01-12 23:24:04 +0100","longitude":-1,"latitude":-1,"altitude":68.0,"accuracy_v":0,"accuracy_h":13,"speed":7.7172346115112305,"duration":715625,"distance":2192,"elevation_gain":96,"elevation_loss":95},
{"version":1,"timestamp":"2018-01-12 23:24:15 +0100","longitude":-1,"latitude":-1,"altitude":71.0,"accuracy_v":0,"accuracy_h":19,"speed":8.034262657165527,"duration":726615,"distance":2225,"elevation_gain":99,"elevation_loss":95},
{"version":1,"timestamp":"2018-01-12 23:24:24 +0100","longitude":-1,"latitude":-1,"altitude":67.0,"accuracy_v":0,"accuracy_h":7,"speed":9.48891830444336,"duration":735614,"distance":2263,"elevation_gain":99,"elevation_loss":99},
{"version":1,"timestamp":"2018-01-12 23:24:41 +0100","longitude":-1,"latitude":-1,"altitude":60.0,"accuracy_v":0,"accuracy_h":15,"speed":4.976312160491943,"duration":752614,"distance":2301,"elevation_gain":99,"elevation_loss":106},
{"version":1,"timestamp":"2018-01-12 23:24:50 +0100","longitude":-1,"latitude":-1,"altitude":59.0,"accuracy_v":0,"accuracy_h":9,"speed":9.190099716186523,"duration":761635,"distance":2336,"elevation_gain":99,"elevation_loss":107},
{"version":1,"timestamp":"2018-01-12 23:25:10 +0100","longitude":-1,"latitude":-1,"altitude":62.0,"accuracy_v":0,"accuracy_h":10,"speed":3.390110731124878,"duration":781606,"distance":2374,"elevation_gain":102,"elevation_loss":107},
{"version":1,"timestamp":"2018-01-12 23:25:13 +0100","longitude":-1,"latitude":-1,"altitude":59.0,"accuracy_v":0,"accuracy_h":10,"speed":0.0,"duration":784617,"distance":2375,"elevation_gain":102,"elevation_loss":110},
{"version":1,"timestamp":"2018-01-12 23:25:28 +0100","longitude":-1,"latitude":-1,"altitude":63.0,"accuracy_v":0,"accuracy_h":7,"speed":0.0,"duration":799614,"distance":2379,"elevation_gain":106,"elevation_loss":110},
{"version":1,"timestamp":"2018-01-12 23:25:29 +0100","longitude":-1,"latitude":-1,"altitude":63.0,"accuracy_v":0,"accuracy_h":7,"speed":0.5632460117340088,"duration":800614,"distance":2382,"elevation_gain":106,"elevation_loss":110},
{"version":1,"timestamp":"2018-01-12 23:25:45 +0100","longitude":-1,"latitude":-1,"altitude":65.0,"accuracy_v":0,"accuracy_h":7,"speed":3.826239824295044,"duration":816613,"distance":2416,"elevation_gain":108,"elevation_loss":110},
{"version":1,"timestamp":"2018-01-12 23:25:47 +0100","longitude":-1,"latitude":-1,"altitude":64.0,"accuracy_v":0,"accuracy_h":6,"speed":4.104000091552734,"duration":818608,"distance":2424,"elevation_gain":108,"elevation_loss":111},
{"version":1,"timestamp":"2018-01-12 23:25:47 +0100","longitude":-1,"latitude":-1,"altitude":64.0,"accuracy_v":0,"accuracy_h":6,"speed":4.104000091552734,"duration":818951,"distance":2424,"elevation_gain":108,"elevation_loss":111}]
