[{"version":1,"timestamp":"2018-01-30 23:06:23 +0100","longitude":-1,"latitude":-1,"altitude":65.0,"accuracy_v":0,"accuracy_h":7,"speed":0.0,"duration":2418,"distance":0,"elevation_gain":0,"elevation_loss":0},
{"version":1,"timestamp":"2018-01-30 23:06:24 +0100","longitude":-1,"latitude":-1,"altitude":62.0,"accuracy_v":0,"accuracy_h":7,"speed":0.0,"duration":3420,"distance":0,"elevation_gain":0,"elevation_loss":3},
{"version":1,"timestamp":"2018-01-30 23:06:32 +0100","longitude":-1,"latitude":-1,"altitude":67.0,"accuracy_v":0,"accuracy_h":13,"speed":0.0,"duration":11406,"distance":2,"elevation_gain":5,"elevation_loss":3},
{"version":1,"timestamp":"2018-01-30 23:06:33 +0100","longitude":-1,"latitude":-1,"altitude":67.0,"accuracy_v":0,"accuracy_h":13,"speed":0.4527774155139923,"duration":12406,"distance":3,"elevation_gain":5,"elevation_loss":3},
{"version":1,"timestamp":"2018-01-30 23:06:44 +0100","longitude":-1,"latitude":-1,"altitude":64.0,"accuracy_v":0,"accuracy_h":12,"speed":7.86624002456665,"duration":23426,"distance":38,"elevation_gain":5,"elevation_loss":6},
{"version":1,"timestamp":"2018-01-30 23:06:56 +0100","longitude":-1,"latitude":-1,"altitude":66.0,"accuracy_v":0,"accuracy_h":12,"speed":7.986515998840332,"duration":35417,"distance":74,"elevation_gain":7,"elevation_loss":6},
{"version":1,"timestamp":"2018-01-30 23:07:10 +0100","longitude":-1,"latitude":-1,"altitude":65.0,"accuracy_v":0,"accuracy_h":7,"speed":5.479922294616699,"duration":49445,"distance":110,"elevation_gain":7,"elevation_loss":7},
{"version":1,"timestamp":"2018-01-30 23:07:23 +0100","longitude":-1,"latitude":-1,"altitude":67.0,"accuracy_v":0,"accuracy_h":10,"speed":8.889983177185059,"duration":62419,"distance":146,"elevation_gain":9,"elevation_loss":7},
{"version":1,"timestamp":"2018-01-30 23:07:39 +0100","longitude":-1,"latitude":-1,"altitude":59.0,"accuracy_v":0,"accuracy_h":13,"speed":6.691848278045654,"duration":78415,"distance":179,"elevation_gain":9,"elevation_loss":15},
{"version":1,"timestamp":"2018-01-30 23:07:57 +0100","longitude":-1,"latitude":-1,"altitude":51.0,"accuracy_v":0,"accuracy_h":15,"speed":4.563851833343506,"duration":96423,"distance":210,"elevation_gain":9,"elevation_loss":23},
{"version":1,"timestamp":"2018-01-30 23:08:06 +0100","longitude":-1,"latitude":-1,"altitude":63.0,"accuracy_v":0,"accuracy_h":13,"speed":8.99683952331543,"duration":105424,"distance":243,"elevation_gain":21,"elevation_loss":23},
{"version":1,"timestamp":"2018-01-30 23:08:13 +0100","longitude":-1,"latitude":-1,"altitude":68.0,"accuracy_v":0,"accuracy_h":15,"speed":11.696446418762207,"duration":112419,"distance":273,"elevation_gain":26,"elevation_loss":23},
{"version":1,"timestamp":"2018-01-30 23:08:23 +0100","longitude":-1,"latitude":-1,"altitude":73.0,"accuracy_v":0,"accuracy_h":9,"speed":10.44286823272705,"duration":122425,"distance":310,"elevation_gain":31,"elevation_loss":23},
{"version":1,"timestamp":"2018-01-30 23:08:37 +0100","longitude":-1,"latitude":-1,"altitude":84.0,"accuracy_v":0,"accuracy_h":13,"speed":6.579316139221191,"duration":136423,"distance":345,"elevation_gain":42,"elevation_loss":23},
{"version":1,"timestamp":"2018-01-30 23:08:49 +0100","longitude":-1,"latitude":-1,"altitude":90.0,"accuracy_v":0,"accuracy_h":12,"speed":4.9071455001831055,"duration":148424,"distance":378,"elevation_gain":48,"elevation_loss":23},
{"version":1,"timestamp":"2018-01-30 23:09:01 +0100","longitude":-1,"latitude":-1,"altitude":88.0,"accuracy_v":0,"accuracy_h":18,"speed":5.635119438171387,"duration":160422,"distance":402,"elevation_gain":48,"elevation_loss":25},
{"version":1,"timestamp":"2018-01-30 23:09:08 +0100","longitude":-1,"latitude":-1,"altitude":88.0,"accuracy_v":0,"accuracy_h":16,"speed":5.902457237243652,"duration":167419,"distance":416,"elevation_gain":48,"elevation_loss":25},
{"version":1,"timestamp":"2018-01-30 23:09:14 +0100","longitude":-1,"latitude":-1,"altitude":94.0,"accuracy_v":0,"accuracy_h":15,"speed":5.6686015129089355,"duration":173422,"distance":445,"elevation_gain":54,"elevation_loss":25},
{"version":1,"timestamp":"2018-01-30 23:09:23 +0100","longitude":-1,"latitude":-1,"altitude":77.0,"accuracy_v":0,"accuracy_h":16,"speed":7.774771690368652,"duration":182426,"distance":476,"elevation_gain":54,"elevation_loss":42},
{"version":1,"timestamp":"2018-01-30 23:09:29 +0100","longitude":-1,"latitude":-1,"altitude":72.0,"accuracy_v":0,"accuracy_h":18,"speed":7.694565773010254,"duration":188427,"distance":502,"elevation_gain":54,"elevation_loss":47},
{"version":1,"timestamp":"2018-01-30 23:09:34 +0100","longitude":-1,"latitude":-1,"altitude":68.0,"accuracy_v":0,"accuracy_h":13,"speed":10.121374130249023,"duration":193420,"distance":536,"elevation_gain":54,"elevation_loss":51},
{"version":1,"timestamp":"2018-01-30 23:09:42 +0100","longitude":-1,"latitude":-1,"altitude":78.0,"accuracy_v":0,"accuracy_h":12,"speed":11.967034339904785,"duration":201418,"distance":577,"elevation_gain":64,"elevation_loss":51},
{"version":1,"timestamp":"2018-01-30 23:09:54 +0100","longitude":-1,"latitude":-1,"altitude":76.0,"accuracy_v":0,"accuracy_h":12,"speed":10.284934997558594,"duration":213427,"distance":616,"elevation_gain":64,"elevation_loss":53},
{"version":1,"timestamp":"2018-01-30 23:10:06 +0100","longitude":-1,"latitude":-1,"altitude":78.0,"accuracy_v":0,"accuracy_h":9,"speed":11.014629364013672,"duration":225428,"distance":655,"elevation_gain":66,"elevation_loss":53},
{"version":1,"timestamp":"2018-01-30 23:10:23 +0100","longitude":-1,"latitude":-1,"altitude":80.0,"accuracy_v":0,"accuracy_h":10,"speed":6.059197425842285,"duration":242419,"distance":692,"elevation_gain":68,"elevation_loss":53},
{"version":1,"timestamp":"2018-01-30 23:10:32 +0100","longitude":-1,"latitude":-1,"altitude":81.0,"accuracy_v":0,"accuracy_h":10,"speed":10.790946960449219,"duration":251419,"distance":730,"elevation_gain":69,"elevation_loss":53},
{"version":1,"timestamp":"2018-01-30 23:10:42 +0100","longitude":-1,"latitude":-1,"altitude":78.0,"accuracy_v":0,"accuracy_h":9,"speed":9.186842918395996,"duration":261423,"distance":767,"elevation_gain":69,"elevation_loss":56},
{"version":1,"timestamp":"2018-01-30 23:10:52 +0100","longitude":-1,"latitude":-1,"altitude":75.0,"accuracy_v":0,"accuracy_h":7,"speed":6.077230453491211,"duration":271418,"distance":789,"elevation_gain":69,"elevation_loss":59},
{"version":1,"timestamp":"2018-01-30 23:11:01 +0100","longitude":-1,"latitude":-1,"altitude":68.0,"accuracy_v":0,"accuracy_h":16,"speed":9.425305366516113,"duration":280415,"distance":811,"elevation_gain":69,"elevation_loss":66},
{"version":1,"timestamp":"2018-01-30 23:11:15 +0100","longitude":-1,"latitude":-1,"altitude":65.0,"accuracy_v":0,"accuracy_h":19,"speed":7.510648727416992,"duration":294421,"distance":846,"elevation_gain":69,"elevation_loss":69},
{"version":1,"timestamp":"2018-01-30 23:11:26 +0100","longitude":-1,"latitude":-1,"altitude":74.0,"accuracy_v":0,"accuracy_h":16,"speed":6.597569465637207,"duration":305422,"distance":870,"elevation_gain":78,"elevation_loss":69},
{"version":1,"timestamp":"2018-01-30 23:11:31 +0100","longitude":-1,"latitude":-1,"altitude":77.0,"accuracy_v":0,"accuracy_h":9,"speed":7.848463535308838,"duration":310426,"distance":906,"elevation_gain":81,"elevation_loss":69},
{"version":1,"timestamp":"2018-01-30 23:11:42 +0100","longitude":-1,"latitude":-1,"altitude":76.0,"accuracy_v":0,"accuracy_h":9,"speed":6.3382887840271,"duration":321429,"distance":944,"elevation_gain":81,"elevation_loss":70},
{"version":1,"timestamp":"2018-01-30 23:11:54 +0100","longitude":-1,"latitude":-1,"altitude":74.0,"accuracy_v":0,"accuracy_h":12,"speed":6.788028240203857,"duration":333415,"distance":982,"elevation_gain":81,"elevation_loss":72},
{"version":1,"timestamp":"2018-01-30 23:12:08 +0100","longitude":-1,"latitude":-1,"altitude":73.0,"accuracy_v":0,"accuracy_h":12,"speed":6.320883750915527,"duration":347422,"distance":1012,"elevation_gain":81,"elevation_loss":73},
{"version":1,"timestamp":"2018-01-30 23:12:18 +0100","longitude":-1,"latitude":-1,"altitude":70.0,"accuracy_v":0,"accuracy_h":9,"speed":6.604838848114014,"duration":357422,"distance":1049,"elevation_gain":81,"elevation_loss":76},
{"version":1,"timestamp":"2018-01-30 23:12:23 +0100","longitude":-1,"latitude":-1,"altitude":69.0,"accuracy_v":0,"accuracy_h":10,"speed":8.064613342285156,"duration":362426,"distance":1069,"elevation_gain":81,"elevation_loss":77},
{"version":1,"timestamp":"2018-01-30 23:12:28 +0100","longitude":-1,"latitude":-1,"altitude":70.0,"accuracy_v":0,"accuracy_h":7,"speed":9.026155471801758,"duration":367424,"distance":1089,"elevation_gain":82,"elevation_loss":77},
{"version":1,"timestamp":"2018-01-30 23:12:43 +0100","longitude":-1,"latitude":-1,"altitude":67.0,"accuracy_v":0,"accuracy_h":12,"speed":6.565627574920654,"duration":382429,"distance":1127,"elevation_gain":82,"elevation_loss":80},
{"version":1,"timestamp":"2018-01-30 23:12:58 +0100","longitude":-1,"latitude":-1,"altitude":62.0,"accuracy_v":0,"accuracy_h":12,"speed":4.995794296264648,"duration":397422,"distance":1153,"elevation_gain":82,"elevation_loss":85},
{"version":1,"timestamp":"2018-01-30 23:13:09 +0100","longitude":-1,"latitude":-1,"altitude":65.0,"accuracy_v":0,"accuracy_h":12,"speed":3.9594674110412598,"duration":408428,"distance":1183,"elevation_gain":85,"elevation_loss":85},
{"version":1,"timestamp":"2018-01-30 23:13:16 +0100","longitude":-1,"latitude":-1,"altitude":75.0,"accuracy_v":0,"accuracy_h":18,"speed":8.41689395904541,"duration":415421,"distance":1219,"elevation_gain":95,"elevation_loss":85},
{"version":1,"timestamp":"2018-01-30 23:13:26 +0100","longitude":-1,"latitude":-1,"altitude":81.0,"accuracy_v":0,"accuracy_h":9,"speed":7.792090892791748,"duration":425423,"distance":1257,"elevation_gain":101,"elevation_loss":85},
{"version":1,"timestamp":"2018-01-30 23:13:35 +0100","longitude":-1,"latitude":-1,"altitude":81.0,"accuracy_v":0,"accuracy_h":10,"speed":5.213770389556885,"duration":434438,"distance":1277,"elevation_gain":101,"elevation_loss":85},
{"version":1,"timestamp":"2018-01-30 23:13:43 +0100","longitude":-1,"latitude":-1,"altitude":80.0,"accuracy_v":0,"accuracy_h":10,"speed":6.243161201477051,"duration":442426,"distance":1299,"elevation_gain":101,"elevation_loss":86},
{"version":1,"timestamp":"2018-01-30 23:13:53 +0100","longitude":-1,"latitude":-1,"altitude":82.0,"accuracy_v":0,"accuracy_h":10,"speed":7.93330717086792,"duration":452415,"distance":1336,"elevation_gain":103,"elevation_loss":86},
{"version":1,"timestamp":"2018-01-30 23:14:06 +0100","longitude":-1,"latitude":-1,"altitude":71.0,"accuracy_v":0,"accuracy_h":10,"speed":9.287324905395508,"duration":465423,"distance":1376,"elevation_gain":103,"elevation_loss":97},
{"version":1,"timestamp":"2018-01-30 23:14:21 +0100","longitude":-1,"latitude":-1,"altitude":68.0,"accuracy_v":0,"accuracy_h":10,"speed":6.11880350112915,"duration":480411,"distance":1410,"elevation_gain":103,"elevation_loss":100},
{"version":1,"timestamp":"2018-01-30 23:14:31 +0100","longitude":-1,"latitude":-1,"altitude":74.0,"accuracy_v":0,"accuracy_h":13,"speed":8.43808650970459,"duration":490427,"distance":1446,"elevation_gain":109,"elevation_loss":100},
{"version":1,"timestamp":"2018-01-30 23:14:46 +0100","longitude":-1,"latitude":-1,"altitude":69.0,"accuracy_v":0,"accuracy_h":13,"speed":6.207062244415283,"duration":505420,"distance":1479,"elevation_gain":109,"elevation_loss":105},
{"version":1,"timestamp":"2018-01-30 23:14:54 +0100","longitude":-1,"latitude":-1,"altitude":72.0,"accuracy_v":0,"accuracy_h":7,"speed":7.975709438323975,"duration":513419,"distance":1514,"elevation_gain":112,"elevation_loss":105},
{"version":1,"timestamp":"2018-01-30 23:15:03 +0100","longitude":-1,"latitude":-1,"altitude":76.0,"accuracy_v":0,"accuracy_h":6,"speed":10.080914497375488,"duration":522421,"distance":1556,"elevation_gain":116,"elevation_loss":105},
{"version":1,"timestamp":"2018-01-30 23:15:18 +0100","longitude":-1,"latitude":-1,"altitude":70.0,"accuracy_v":0,"accuracy_h":10,"speed":9.134593963623047,"duration":537410,"distance":1596,"elevation_gain":116,"elevation_loss":111},
{"version":1,"timestamp":"2018-01-30 23:15:30 +0100","longitude":-1,"latitude":-1,"altitude":74.0,"accuracy_v":0,"accuracy_h":10,"speed":8.287161827087402,"duration":549422,"distance":1633,"elevation_gain":120,"elevation_loss":111},
{"version":1,"timestamp":"2018-01-30 23:15:42 +0100","longitude":-1,"latitude":-1,"altitude":73.0,"accuracy_v":0,"accuracy_h":12,"speed":6.522846221923828,"duration":561419,"distance":1669,"elevation_gain":120,"elevation_loss":112},
{"version":1,"timestamp":"2018-01-30 23:15:53 +0100","longitude":-1,"latitude":-1,"altitude":69.0,"accuracy_v":0,"accuracy_h":12,"speed":6.205280780792236,"duration":572418,"distance":1703,"elevation_gain":120,"elevation_loss":116},
{"version":1,"timestamp":"2018-01-30 23:16:05 +0100","longitude":-1,"latitude":-1,"altitude":67.0,"accuracy_v":0,"accuracy_h":10,"speed":5.580179214477539,"duration":584423,"distance":1734,"elevation_gain":120,"elevation_loss":118},
{"version":1,"timestamp":"2018-01-30 23:16:13 +0100","longitude":-1,"latitude":-1,"altitude":70.0,"accuracy_v":0,"accuracy_h":6,"speed":9.666025161743164,"duration":592426,"distance":1773,"elevation_gain":123,"elevation_loss":118},
{"version":1,"timestamp":"2018-01-30 23:16:27 +0100","longitude":-1,"latitude":-1,"altitude":66.0,"accuracy_v":0,"accuracy_h":13,"speed":8.049159049987793,"duration":606419,"distance":1809,"elevation_gain":123,"elevation_loss":122},
{"version":1,"timestamp":"2018-01-30 23:16:38 +0100","longitude":-1,"latitude":-1,"altitude":66.0,"accuracy_v":0,"accuracy_h":13,"speed":7.829955101013184,"duration":617425,"distance":1842,"elevation_gain":123,"elevation_loss":122},
{"version":1,"timestamp":"2018-01-30 23:16:49 +0100","longitude":-1,"latitude":-1,"altitude":63.0,"accuracy_v":0,"accuracy_h":10,"speed":6.0776495933532715,"duration":628425,"distance":1874,"elevation_gain":123,"elevation_loss":125},
{"version":1,"timestamp":"2018-01-30 23:17:01 +0100","longitude":-1,"latitude":-1,"altitude":54.0,"accuracy_v":0,"accuracy_h":9,"speed":7.393996715545654,"duration":640420,"distance":1911,"elevation_gain":123,"elevation_loss":134},
{"version":1,"timestamp":"2018-01-30 23:17:11 +0100","longitude":-1,"latitude":-1,"altitude":58.0,"accuracy_v":0,"accuracy_h":7,"speed":10.531675338745117,"duration":650419,"distance":1950,"elevation_gain":127,"elevation_loss":134},
{"version":1,"timestamp":"2018-01-30 23:17:24 +0100","longitude":-1,"latitude":-1,"altitude":65.0,"accuracy_v":0,"accuracy_h":9,"speed":7.3976335525512695,"duration":663416,"distance":1988,"elevation_gain":134,"elevation_loss":134},
{"version":1,"timestamp":"2018-01-30 23:17:33 +0100","longitude":-1,"latitude":-1,"altitude":66.0,"accuracy_v":0,"accuracy_h":9,"speed":10.45065689086914,"duration":672425,"distance":2024,"elevation_gain":135,"elevation_loss":134},
{"version":1,"timestamp":"2018-01-30 23:17:46 +0100","longitude":-1,"latitude":-1,"altitude":60.0,"accuracy_v":0,"accuracy_h":12,"speed":6.945905685424805,"duration":685426,"distance":2059,"elevation_gain":135,"elevation_loss":140},
{"version":1,"timestamp":"2018-01-30 23:17:54 +0100","longitude":-1,"latitude":-1,"altitude":68.0,"accuracy_v":0,"accuracy_h":6,"speed":10.767200469970703,"duration":693424,"distance":2099,"elevation_gain":143,"elevation_loss":140},
{"version":1,"timestamp":"2018-01-30 23:18:11 +0100","longitude":-1,"latitude":-1,"altitude":59.0,"accuracy_v":0,"accuracy_h":10,"speed":4.547494411468506,"duration":710433,"distance":2133,"elevation_gain":143,"elevation_loss":149},
{"version":1,"timestamp":"2018-01-30 23:18:22 +0100","longitude":-1,"latitude":-1,"altitude":55.0,"accuracy_v":0,"accuracy_h":15,"speed":6.659026622772217,"duration":721419,"distance":2166,"elevation_gain":143,"elevation_loss":153},
{"version":1,"timestamp":"2018-01-30 23:18:29 +0100","longitude":-1,"latitude":-1,"altitude":48.0,"accuracy_v":0,"accuracy_h":12,"speed":7.915195941925049,"duration":728423,"distance":2197,"elevation_gain":143,"elevation_loss":160},
{"version":1,"timestamp":"2018-01-30 23:18:36 +0100","longitude":-1,"latitude":-1,"altitude":61.0,"accuracy_v":0,"accuracy_h":12,"speed":9.727619171142578,"duration":735422,"distance":2228,"elevation_gain":156,"elevation_loss":160},
{"version":1,"timestamp":"2018-01-30 23:18:45 +0100","longitude":-1,"latitude":-1,"altitude":64.0,"accuracy_v":0,"accuracy_h":12,"speed":8.473183631896973,"duration":744422,"distance":2261,"elevation_gain":159,"elevation_loss":160},
{"version":1,"timestamp":"2018-01-30 23:18:54 +0100","longitude":-1,"latitude":-1,"altitude":60.0,"accuracy_v":0,"accuracy_h":15,"speed":8.379572868347168,"duration":753417,"distance":2295,"elevation_gain":159,"elevation_loss":164},
{"version":1,"timestamp":"2018-01-30 23:19:06 +0100","longitude":-1,"latitude":-1,"altitude":57.0,"accuracy_v":0,"accuracy_h":12,"speed":6.9704766273498535,"duration":765424,"distance":2333,"elevation_gain":159,"elevation_loss":167},
{"version":1,"timestamp":"2018-01-30 23:19:16 +0100","longitude":-1,"latitude":-1,"altitude":51.0,"accuracy_v":0,"accuracy_h":10,"speed":10.272527694702148,"duration":775428,"distance":2373,"elevation_gain":159,"elevation_loss":173},
{"version":1,"timestamp":"2018-01-30 23:19:24 +0100","longitude":-1,"latitude":-1,"altitude":53.0,"accuracy_v":0,"accuracy_h":9,"speed":9.521151542663574,"duration":783426,"distance":2401,"elevation_gain":161,"elevation_loss":173},
{"version":1,"timestamp":"2018-01-30 23:19:35 +0100","longitude":-1,"latitude":-1,"altitude":62.0,"accuracy_v":0,"accuracy_h":7,"speed":3.0456836223602295,"duration":794425,"distance":2414,"elevation_gain":170,"elevation_loss":173},
{"version":1,"timestamp":"2018-01-30 23:19:40 +0100","longitude":-1,"latitude":-1,"altitude":62.0,"accuracy_v":0,"accuracy_h":7,"speed":2.1600000858306885,"duration":799411,"distance":2422,"elevation_gain":170,"elevation_loss":173},
{"version":1,"timestamp":"2018-01-30 23:19:40 +0100","longitude":-1,"latitude":-1,"altitude":62.0,"accuracy_v":0,"accuracy_h":7,"speed":2.1600000858306885,"duration":799874,"distance":2422,"elevation_gain":170,"elevation_loss":173}]
